{
    "description": "项目私有配置文件。此文件中的内容将覆盖 project.config.json 中的相同字段。项目的改动优先同步到此文件中。详见文档：https://developers.weixin.qq.com/miniprogram/dev/devtools/projectconfig.html",
    "projectname": "IntelligentHousekeep",
    "setting": {
        "ignoreDevUnusedFiles": false,
        "compileHotReLoad": true,
        "urlCheck": false
    },
    "condition": {
        "miniprogram": {
            "list": [
                {
                    "name": "搜索蓝牙设备页面",
                    "pathName": "pages/search/searchBluetoothDevices",
                    "query": "",
                    "launchMode": "default",
                    "scene": null
                },
                {
                    "name": "设备界面",
                    "pathName": "pages/bluetoothDevices/bluetoothDevicesManage",
                    "query": "deviceId=34:23:42&deviceName=MyESP",
                    "launchMode": "default",
                    "scene": null
                },
                {
                    "name": "设置WIFI",
                    "pathName": "pages/bluetoothDevices/setWifi/setWifi",
                    "query": "",
                    "launchMode": "default",
                    "scene": null
                },
                {
                    "name": "灯控",
                    "pathName": "pages/bluetoothDevices/led/lampManage",
                    "query": "",
                    "launchMode": "default",
                    "scene": null
                }
            ]
        }
    }
}